{
  "title": "物理设置模板",
  "version": "1.0",
  "game_name": "{GameName}",
  "dependencies": [
    "场景搭建"
  ],
  "stories": [
    {
      "id": "physics-001",
      "category": "global_settings",
      "description": "Physics全局参数",
      "details": "访问路径: Edit > Project Settings > Physics | 重力: (0, -9.81, 0) | Default Material: Default.physicMaterial | Sleep Threshold: 0.005 | Default Solver Iterations: 6 | Default Solver Velocity Iterations: 1 | Default Contact Offset: 0.01 | Auto Simulation: 启用 | Auto Sync Transforms: 启用",
      "passes": false
    },
    {
      "id": "physics-002",
      "category": "physic_material",
      "description": "默认物理材质 Default.physicMaterial",
      "details": "Dynamic Friction: 0.6 | Static Friction: 0.6 | Bounciness: 0 | Friction Combine: Average | Bounce Combine: Average",
      "passes": false
    },
    {
      "id": "physics-003",
      "category": "physic_material",
      "description": "Player物理材质 Player.physicMaterial",
      "details": "Dynamic Friction: 0 | Static Friction: 0 | Bounciness: 0 | Friction Combine: Minimum | Bounce Combine: Minimum | 用途: 减少玩家移动摩擦力，使控制更流畅",
      "passes": false
    },
    {
      "id": "physics-004",
      "category": "physic_material",
      "description": "Ground物理材质 Ground.physicMaterial",
      "details": "Dynamic Friction: 0.6 | Static Friction: 0.6 | Bounciness: 0 | Friction Combine: Average | Bounce Combine: Average | 用途: 地面正常摩擦力，提供稳定的站立和移动",
      "passes": false
    },
    {
      "id": "physics-005",
      "category": "physic_material",
      "description": "Bouncy物理材质 Bouncy.physicMaterial（可选）",
      "details": "Dynamic Friction: 0 | Static Friction: 0 | Bounciness: 1 | Friction Combine: Minimum | Bounce Combine: Maximum | 用途: 弹跳平台或弹力道具",
      "passes": false
    },
    {
      "id": "physics-006",
      "category": "prefab_physics",
      "description": "Player Prefab Rigidbody配置",
      "details": "Mass: 1 | Drag: 0 | Angular Drag: 0.05 | Use Gravity: 启用 | Is Kinematic: 禁用 | Interpolate: Interpolate | Collision Detection: Continuous Dynamic | Constraints: Freeze Position Z ✓, Freeze Rotation X ✓, Freeze Rotation Y ✓, Freeze Rotation Z ✓",
      "passes": false
    },
    {
      "id": "physics-007",
      "category": "prefab_physics",
      "description": "Player Prefab Collider配置",
      "details": "Material: Player.physicMaterial | Is Trigger: 禁用 | Size: 根据模型调整 | Center: 根据模型调整",
      "passes": false
    },
    {
      "id": "physics-008",
      "category": "prefab_physics",
      "description": "Enemy Prefab物理配置",
      "details": "Rigidbody: Mass 1, Drag 0, Use Gravity 启用, Is Kinematic 禁用（或根据AI类型启用）, Collision Detection Discrete | Collider: Material Default.physicMaterial, Is Trigger 禁用",
      "passes": false
    },
    {
      "id": "physics-009",
      "category": "prefab_physics",
      "description": "Collectible Prefab物理配置",
      "details": "Rigidbody: Mass 0.1, Drag 0, Use Gravity 禁用, Is Kinematic 启用, Interpolate None | Collider: Material 无（或Bouncy.physicMaterial）, Is Trigger 启用",
      "passes": false
    },
    {
      "id": "physics-010",
      "category": "scene_physics",
      "description": "Platform静态碰撞器",
      "details": "对象: Platform实例（无Rigidbody） | Collider: Material Ground.physicMaterial, Is Trigger 禁用",
      "passes": false
    },
    {
      "id": "physics-011",
      "category": "scene_physics",
      "description": "Ground静态碰撞器",
      "details": "对象: Ground对象（无Rigidbody） | Collider: Material Ground.physicMaterial, Is Trigger 禁用",
      "passes": false
    },
    {
      "id": "physics-012",
      "category": "scene_physics",
      "description": "Obstacle静态碰撞器",
      "details": "对象: Obstacle对象（无Rigidbody） | Collider: Material Default.physicMaterial, Is Trigger 禁用",
      "passes": false
    }
  ]
}